LICENSE.md
MANIFEST.in
README.md
setup.py
CodeCounter/CodeCounter.py
CodeCounter/__init__.py
CodeCounter/filerange.py
CodeCounter/parser.yml
CodeCounter.egg-info/PKG-INFO
CodeCounter.egg-info/SOURCES.txt
CodeCounter.egg-info/dependency_links.txt
CodeCounter.egg-info/entry_points.txt
CodeCounter.egg-info/not-zip-safe
CodeCounter.egg-info/requires.txt
CodeCounter.egg-info/top_level.txt