Metadata-Version: 1.1
Name: CodeCounter
Version: 1.1.0
Summary: CoderCounter is a program can canculate code file line,such ass python,javasript,html,config etc which ignore code comments and blank code line.
Home-page: https://gitlab.com/wekay102200/CodeCounter.git
Author: wukan
Author-email: kan.wu@gengtalks.com
License: Genetalks
Platform: UNKNOWN
Classifier: Development Status :: 4 - Beta
Classifier: Environment :: Console
Classifier: Operating System :: OS Independent
Classifier: Programming Language :: Python
Classifier: Topic :: Software Development :: Libraries :: Python Modules
Classifier: Programming Language :: Python :: 2.5
Classifier: Programming Language :: Python :: 2.6
Classifier: Programming Language :: Python :: 2.7
Classifier: Programming Language :: Python :: Implementation :: CPython
Classifier: Programming Language :: Python :: Implementation :: PyPy
